swpwn/__init__.py
swpwn/swpwn.py
swpwn-1.0.4.dist-info/METADATA
swpwn-1.0.4.dist-info/WHEEL
swpwn-1.0.4.dist-info/entry_points.txt
swpwn-1.0.4.dist-info/top_level.txt
swpwn-1.0.4.dist-info/RECORD
