Metadata-Version: 2.1
Name: swpwn
Version: 1.0.4
Summary: swpwn docker image manipulation script, to simplify docker pwn environment management
Home-page: UNKNOWN
Author: swing
Author-email: UNKNOWN
License: UNKNOWN
Platform: UNKNOWN
Requires-Dist: docker
